{
  "metadata": {
    "version": 4.5,
    "type": "Object",
    "generator": "Object3D.toJSON"
  },
  "camera": {
    "position": [
      0,
      4,
      5
    ],
    "fov": 75
  },
  "geometries": [
    {
      "uuid": "057766C8-4668-476F-A283-7B25D97D3941",
      "type": "BoxGeometry",
      "width": 1,
      "height": 0.01,
      "depth": 0.75,
      "widthSegments": 1,
      "heightSegments": 1,
      "depthSegments": 1
    },
    {
      "uuid": "68AB17BE-D311-4C8F-A4AA-EC7CBBAA44E1",
      "type": "BoxGeometry",
      "width": 1,
      "height": 0.01,
      "depth": 1,
      "widthSegments": 1,
      "heightSegments": 1,
      "depthSegments": 1
    },
    {
      "uuid": "9620A241-34A5-4BEC-8242-3E717FE32AE8",
      "type": "BoxGeometry",
      "width": 1,
      "height": 0.01,
      "depth": 1.5,
      "widthSegments": 1,
      "heightSegments": 1,
      "depthSegments": 1
    },
    {
      "uuid": "E38C38A8-DA21-45A6-8C1F-FF913A555003",
      "type": "BoxGeometry",
      "width": 1,
      "height": 0.01,
      "depth": 1.25,
      "widthSegments": 1,
      "heightSegments": 1,
      "depthSegments": 1
    },
    {
      "uuid": "249150A3-6DD8-4DA0-9103-DF6F86E5EC06",
      "type": "BoxGeometry",
      "width": 1,
      "height": 0.01,
      "depth": 1,
      "widthSegments": 1,
      "heightSegments": 1,
      "depthSegments": 1
    },
    {
      "uuid": "F2481688-8870-42FC-917C-9CEADAF9D0B3",
      "type": "BoxGeometry",
      "width": 1,
      "height": 0.01,
      "depth": 0.75,
      "widthSegments": 1,
      "heightSegments": 1,
      "depthSegments": 1
    },
    {
      "uuid": "141ECD77-67FA-4117-A044-8623F4059DCF",
      "type": "PlaneGeometry",
      "width": 100,
      "height": 100,
      "widthSegments": 1,
      "heightSegments": 1
    }
  ],
  "materials": [
    {
      "uuid": "171BCB11-F83C-4B61-9147-BC9DF4CD4ABF",
      "type": "MeshStandardMaterial",
      "color": 0,
      "roughness": 1,
      "metalness": 0,
      "emissive": 0,
      "envMapIntensity": 1,
      "refractionRatio": 0.98,
      "depthFunc": 3,
      "depthTest": true,
      "depthWrite": true,
      "colorWrite": true,
      "stencilWrite": false,
      "stencilWriteMask": 255,
      "stencilFunc": 519,
      "stencilRef": 0,
      "stencilFuncMask": 255,
      "stencilFail": 7680,
      "stencilZFail": 7680,
      "stencilZPass": 7680
    },
    {
      "uuid": "01C71024-FD33-49F5-921F-1B519E3F9831",
      "type": "MeshStandardMaterial",
      "color": 8026746,
      "roughness": 1,
      "metalness": 0,
      "emissive": 0,
      "envMapIntensity": 1,
      "refractionRatio": 0.98,
      "depthFunc": 3,
      "depthTest": true,
      "depthWrite": true,
      "colorWrite": true,
      "stencilWrite": false,
      "stencilWriteMask": 255,
      "stencilFunc": 519,
      "stencilRef": 0,
      "stencilFuncMask": 255,
      "stencilFail": 7680,
      "stencilZFail": 7680,
      "stencilZPass": 7680
    },
    {
      "uuid": "B0076335-A2AD-42AD-8563-E7903168F5D4",
      "type": "MeshStandardMaterial",
      "color": 0,
      "roughness": 1,
      "metalness": 0,
      "emissive": 0,
      "envMapIntensity": 1,
      "refractionRatio": 0.98,
      "depthFunc": 3,
      "depthTest": true,
      "depthWrite": true,
      "colorWrite": true,
      "stencilWrite": false,
      "stencilWriteMask": 255,
      "stencilFunc": 519,
      "stencilRef": 0,
      "stencilFuncMask": 255,
      "stencilFail": 7680,
      "stencilZFail": 7680,
      "stencilZPass": 7680
    },
    {
      "uuid": "4CBB5407-33B9-4512-9EAB-3617812A7823",
      "type": "MeshStandardMaterial",
      "color": 16777215,
      "roughness": 1,
      "metalness": 0,
      "emissive": 0,
      "envMapIntensity": 1,
      "refractionRatio": 0.98,
      "depthFunc": 3,
      "depthTest": true,
      "depthWrite": true,
      "colorWrite": true,
      "stencilWrite": false,
      "stencilWriteMask": 255,
      "stencilFunc": 519,
      "stencilRef": 0,
      "stencilFuncMask": 255,
      "stencilFail": 7680,
      "stencilZFail": 7680,
      "stencilZPass": 7680
    },
    {
      "uuid": "460A2475-D38E-42DB-8787-7D8B829059CF",
      "type": "MeshStandardMaterial",
      "color": 16777215,
      "roughness": 1,
      "metalness": 0,
      "emissive": 0,
      "envMapIntensity": 1,
      "refractionRatio": 0.98,
      "depthFunc": 3,
      "depthTest": true,
      "depthWrite": true,
      "colorWrite": true,
      "stencilWrite": false,
      "stencilWriteMask": 255,
      "stencilFunc": 519,
      "stencilRef": 0,
      "stencilFuncMask": 255,
      "stencilFail": 7680,
      "stencilZFail": 7680,
      "stencilZPass": 7680
    },
    {
      "uuid": "1CBA7500-7DA7-4062-9F37-9071B8807F4F",
      "type": "MeshStandardMaterial",
      "color": 9605778,
      "roughness": 1,
      "metalness": 0,
      "emissive": 0,
      "envMapIntensity": 1,
      "refractionRatio": 0.98,
      "depthFunc": 3,
      "depthTest": true,
      "depthWrite": true,
      "colorWrite": true,
      "stencilWrite": false,
      "stencilWriteMask": 255,
      "stencilFunc": 519,
      "stencilRef": 0,
      "stencilFuncMask": 255,
      "stencilFail": 7680,
      "stencilZFail": 7680,
      "stencilZPass": 7680
    }
  ],
  "object": {
    "uuid": "5FC9ACA9-2A93-474D-AA32-FACC76551914",
    "type": "Scene",
    "name": "Reckless Logo",
    "userData": {
      "isPatchHidden": false
    },
    "layers": 1,
    "matrix": [
      1,
      0,
      0,
      0,
      0,
      1,
      0,
      0,
      0,
      0,
      1,
      0,
      0,
      0,
      0,
      1
    ],
    "children": [
      {
        "uuid": "1F0AFF04-BE32-494A-A764-1137A90E3D4B",
        "type": "Group",
        "name": "Logo",
        "userData": {
					"isPatchHidden": false
				},
        "layers": 1,
        "matrix": [
          0,
          0,
          0.3333,
          0,
          0,
          0.333,
          0,
          0,
          -0.333,
          0,
          0,
          0,
          0,
          3,
          0,
          1
        ],
        "children": [
          {
            "uuid": "F78CD658-4B78-47DB-B55E-639DC10578D7",
            "type": "Group",
            "name": "R",
            "userData": {
              "isPatchHidden": true
            },
            "layers": 1,
            "matrix": [
              1,
              0,
              0,
              0,
              0,
              1,
              0,
              0,
              0,
              0,
              1,
              0,
              0,
              0,
              2,
              1
            ],
            "children": [
              {
                "uuid": "0829FFE5-E183-48F5-BB24-4D8FD7C6E5A8",
                "type": "Group",
                "name": "R Group",
                "userData": {
                  "isPatchHidden": true
                },
                "layers": 1,
                "matrix": [
                  1,
                  0,
                  0,
                  0,
                  0,
                  1,
                  0,
                  0,
                  0,
                  0,
                  1,
                  0,
                  0,
                  0,
                  0,
                  1
                ],
                "children": [
                  {
                    "uuid": "E16C06CB-A2D6-4010-A3E7-CED68932AD46",
                    "type": "Mesh",
                    "name": "Right R",
                    "castShadow": true,
                    "receiveShadow": true,
                    "userData": {
                      "isPatchHidden": true
                    },
                    "layers": 1,
                    "matrix": [
                      1,
                      0,
                      0,
                      0,
                      0,
                      0,
                      -1,
                      0,
                      0,
                      1,
                      0,
                      0,
                      0,
                      1.13,
                      -1,
                      1
                    ],
                    "geometry": "057766C8-4668-476F-A283-7B25D97D3941",
                    "material": "171BCB11-F83C-4B61-9147-BC9DF4CD4ABF"
                  },
                  {
                    "uuid": "CC55CA26-F535-4C25-A6E0-CD65EBA0EBB4",
                    "type": "Mesh",
                    "name": "Top R",
                    "castShadow": true,
                    "receiveShadow": true,
                    "userData": {
                      "isPatchHidden": true
                    },
                    "layers": 1,
                    "matrix": [
                      1,
                      0,
                      0,
                      0,
                      0,
                      1,
                      0,
                      0,
                      0,
                      0,
                      1,
                      0,
                      0,
                      1.5,
                      -0.494401,
                      1
                    ],
                    "geometry": "68AB17BE-D311-4C8F-A4AA-EC7CBBAA44E1",
                    "material": "01C71024-FD33-49F5-921F-1B519E3F9831"
                  },
                  {
                    "uuid": "B9ED1126-0B48-43E3-9F7F-68104006F032",
                    "type": "Mesh",
                    "name": "Back R",
                    "castShadow": true,
                    "receiveShadow": true,
                    "userData": {
                      "isPatchHidden": true
                    },
                    "layers": 1,
                    "matrix": [
                      1,
                      0,
                      0,
                      0,
                      0,
                      0,
                      -1,
                      0,
                      0,
                      1,
                      0,
                      0,
                      0,
                      0.75,
                      0.002907,
                      1
                    ],
                    "geometry": "9620A241-34A5-4BEC-8242-3E717FE32AE8",
                    "material": "B0076335-A2AD-42AD-8563-E7903168F5D4"
                  },
                  {
                    "uuid": "00CE6282-5AC5-45BF-9795-AA3DB6848C54",
                    "type": "Mesh",
                    "name": "Slash R",
                    "castShadow": true,
                    "receiveShadow": true,
                    "userData": {
                      "isPatchHidden": true
                    },
                    "layers": 1,
                    "matrix": [
                      1,
                      0,
                      0,
                      0,
                      0,
                      0.811064,
                      -0.584958,
                      0,
                      0,
                      0.584958,
                      0.811064,
                      0,
                      0,
                      0.38,
                      -0.5,
                      1
                    ],
                    "geometry": "E38C38A8-DA21-45A6-8C1F-FF913A555003",
                    "material": "4CBB5407-33B9-4512-9EAB-3617812A7823"
                  },
                  {
                    "uuid": "A7D47287-E518-40F6-9100-59BD53D74F98",
                    "type": "Mesh",
                    "name": "Middle R",
                    "castShadow": true,
                    "receiveShadow": true,
                    "userData": {
                      "isPatchHidden": true
                    },
                    "layers": 1,
                    "matrix": [
                      1,
                      0,
                      0,
                      0,
                      0,
                      1,
                      0,
                      0,
                      0,
                      0,
                      1,
                      0,
                      0,
                      0.75,
                      -0.5,
                      1
                    ],
                    "geometry": "249150A3-6DD8-4DA0-9103-DF6F86E5EC06",
                    "material": "460A2475-D38E-42DB-8787-7D8B829059CF"
                  },
                  {
                    "uuid": "BCD36E99-A893-4757-9B1B-4D1FA4031BB1",
                    "type": "Mesh",
                    "name": "Bottom R",
                    "castShadow": true,
                    "receiveShadow": true,
                    "visible": false,
                    "userData": {
                      "isPatchHidden": true
                    },
                    "layers": 1,
                    "matrix": [
                      1,
                      0,
                      0,
                      0,
                      0,
                      1,
                      0,
                      0,
                      0,
                      0,
                      1,
                      0,
                      0,
                      0,
                      -0.5,
                      1
                    ],
                    "geometry": "249150A3-6DD8-4DA0-9103-DF6F86E5EC06",
                    "material": "460A2475-D38E-42DB-8787-7D8B829059CF"
                  }
                ]
              }
            ]
          },
          {
            "uuid": "CB73D6AE-BADF-4279-A05E-0FF2833875D7",
            "type": "Group",
            "name": "E",
            "renderOrder": 1,
            "userData": {
              "isPatchHidden": true
            },
            "layers": 1,
            "matrix": [
              1,
              0,
              0,
              0,
              0,
              1,
              0,
              0,
              0,
              0,
              1,
              0,
              0,
              0,
              1,
              1
            ],
            "children": [
              {
                "uuid": "9DD7EEB7-F932-4162-B197-75381CC4644B",
                "type": "Group",
                "name": "E Group",
                "userData": {
                  "isPatchHidden": true
                },
                "layers": 1,
                "matrix": [
                  1,
                  0,
                  0,
                  0,
                  0,
                  1,
                  0,
                  0,
                  0,
                  0,
                  1,
                  0,
                  0,
                  0,
                  0,
                  1
                ],
                "children": [
                  {
                    "uuid": "F9E417C2-B184-4719-9144-6AE258CC40E1",
                    "type": "Mesh",
                    "name": "Top E",
                    "castShadow": true,
                    "receiveShadow": true,
                    "userData": {
                      "isPatchHidden": true
                    },
                    "layers": 1,
                    "matrix": [
                      1,
                      0,
                      0,
                      0,
                      0,
                      1,
                      0,
                      0,
                      0,
                      0,
                      1,
                      0,
                      0,
                      1.5,
                      -0.494401,
                      1
                    ],
                    "geometry": "68AB17BE-D311-4C8F-A4AA-EC7CBBAA44E1",
                    "material": "01C71024-FD33-49F5-921F-1B519E3F9831"
                  },
                  {
                    "uuid": "6C109FD7-EC67-4938-81A1-643E700F03FE",
                    "type": "Mesh",
                    "name": "Back E",
                    "castShadow": true,
                    "receiveShadow": true,
                    "frustumCulled": false,
                    "userData": {
                      "isPatchHidden": true
                    },
                    "layers": 1,
                    "matrix": [
                      1,
                      0,
                      0,
                      0,
                      0,
                      0,
                      -1,
                      0,
                      0,
                      1,
                      0,
                      0,
                      0,
                      0.75,
                      0.002907,
                      1
                    ],
                    "geometry": "9620A241-34A5-4BEC-8242-3E717FE32AE8",
                    "material": "B0076335-A2AD-42AD-8563-E7903168F5D4"
                  },
                  {
                    "uuid": "B0E28118-821E-4F05-BEFA-D6A5FBA5C1F4",
                    "type": "Mesh",
                    "name": "Bottom E",
                    "castShadow": true,
                    "receiveShadow": true,
                    "userData": {
                      "isPatchHidden": true
                    },
                    "layers": 1,
                    "matrix": [
                      1,
                      0,
                      0,
                      0,
                      0,
                      1,
                      0,
                      0,
                      0,
                      0,
                      1,
                      0,
                      0,
                      0,
                      -0.5,
                      1
                    ],
                    "geometry": "249150A3-6DD8-4DA0-9103-DF6F86E5EC06",
                    "material": "460A2475-D38E-42DB-8787-7D8B829059CF"
                  },
                  {
                    "uuid": "0267E9F8-6E55-4477-9C58-6BFD9C869BBC",
                    "type": "Mesh",
                    "name": "Middle E",
                    "castShadow": true,
                    "receiveShadow": true,
                    "userData": {
                      "isPatchHidden": true
                    },
                    "layers": 1,
                    "matrix": [
                      1,
                      0,
                      0,
                      0,
                      0,
                      1,
                      0,
                      0,
                      0,
                      0,
                      1,
                      0,
                      0,
                      0.75,
                      -0.5,
                      1
                    ],
                    "geometry": "249150A3-6DD8-4DA0-9103-DF6F86E5EC06",
                    "material": "460A2475-D38E-42DB-8787-7D8B829059CF"
                  }
                ]
              }
            ]
          },
          {
            "uuid": "E4B9E81F-F62E-4663-9C25-8E1603802CDE",
            "type": "Group",
            "name": "C",
            "renderOrder": 2,
            "userData": {
              "isPatchHidden": true
            },
            "layers": 1,
            "matrix": [
              1,
              0,
              0,
              0,
              0,
              1,
              0,
              0,
              0,
              0,
              1,
              0,
              0,
              0,
              0,
              1
            ],
            "children": [
              {
                "uuid": "9C93C279-6848-4CA1-ABF3-2F049E4D7227",
                "type": "Group",
                "name": "C Group",
                "userData": {
                  "isPatchHidden": true
                },
                "layers": 1,
                "matrix": [
                  1,
                  0,
                  0,
                  0,
                  0,
                  1,
                  0,
                  0,
                  0,
                  0,
                  1,
                  0,
                  0,
                  0,
                  0,
                  1
                ],
                "children": [
                  {
                    "uuid": "29AC93E2-FF2F-4E7C-8C6C-C86842F3DBFE",
                    "type": "Mesh",
                    "name": "Top C",
                    "castShadow": true,
                    "receiveShadow": true,
                    "userData": {
                      "isPatchHidden": true
                    },
                    "layers": 1,
                    "matrix": [
                      1,
                      0,
                      0,
                      0,
                      0,
                      1,
                      0,
                      0,
                      0,
                      0,
                      1,
                      0,
                      0,
                      1.5,
                      -0.5,
                      1
                    ],
                    "geometry": "68AB17BE-D311-4C8F-A4AA-EC7CBBAA44E1",
                    "material": "01C71024-FD33-49F5-921F-1B519E3F9831"
                  },
                  {
                    "uuid": "A09895FC-0850-4A53-AA1C-F2C64999066F",
                    "type": "Mesh",
                    "name": "Back C",
                    "castShadow": true,
                    "receiveShadow": true,
                    "userData": {
                      "isPatchHidden": true
                    },
                    "layers": 1,
                    "matrix": [
                      1,
                      0,
                      0,
                      0,
                      0,
                      0,
                      -1,
                      0,
                      0,
                      1,
                      0,
                      0,
                      0,
                      0.75,
                      0.002907,
                      1
                    ],
                    "geometry": "9620A241-34A5-4BEC-8242-3E717FE32AE8",
                    "material": "B0076335-A2AD-42AD-8563-E7903168F5D4"
                  },
                  {
                    "uuid": "9FE58841-0E9A-418C-A242-64FC4DE97C77",
                    "type": "Mesh",
                    "name": "Bottom C",
                    "castShadow": true,
                    "receiveShadow": true,
                    "userData": {
                      "isPatchHidden": true
                    },
                    "layers": 1,
                    "matrix": [
                      1,
                      0,
                      0,
                      0,
                      0,
                      1,
                      0,
                      0,
                      0,
                      0,
                      1,
                      0,
                      0,
                      0,
                      -0.5,
                      1
                    ],
                    "geometry": "249150A3-6DD8-4DA0-9103-DF6F86E5EC06",
                    "material": "460A2475-D38E-42DB-8787-7D8B829059CF"
                  }
                ]
              }
            ]
          },
          {
            "uuid": "98EF39C7-6A1B-469E-8258-63E4CC451DEF",
            "type": "Group",
            "name": "K",
            "renderOrder": 3,
            "userData": {
              "isPatchHidden": true
            },
            "layers": 1,
            "matrix": [
              1,
              0,
              0,
              0,
              0,
              1,
              0,
              0,
              0,
              0,
              1,
              0,
              0,
              0,
              -1,
              1
            ],
            "children": [
              {
                "uuid": "E5EFAB06-D824-4F1D-8532-ECE33C1E3DD7",
                "type": "Group",
                "name": "K Group",
                "userData": {
                  "isPatchHidden": true
                },
                "layers": 1,
                "matrix": [
                  1,
                  0,
                  0,
                  0,
                  0,
                  1,
                  0,
                  0,
                  0,
                  0,
                  1,
                  0,
                  0,
                  0,
                  0,
                  1
                ],
                "children": [
                  {
                    "uuid": "358D7D56-B67E-45AD-BF61-71F20169012B",
                    "type": "Mesh",
                    "name": "Top Slash K",
                    "castShadow": true,
                    "receiveShadow": true,
                    "userData": {
                      "isPatchHidden": true
                    },
                    "layers": 1,
                    "matrix": [
                      1,
                      0,
                      0,
                      0,
                      0,
                      0.811064,
                      0.584958,
                      0,
                      0,
                      -0.584958,
                      0.811064,
                      0,
                      0,
                      1.12,
                      -0.5,
                      1
                    ],
                    "geometry": "E38C38A8-DA21-45A6-8C1F-FF913A555003",
                    "material": "4CBB5407-33B9-4512-9EAB-3617812A7823"
                  },
                  {
                    "uuid": "3E4A6B58-98A7-4EDA-9CCC-631A0549D804",
                    "type": "Mesh",
                    "name": "Bottom Slash K",
                    "castShadow": true,
                    "receiveShadow": true,
                    "userData": {
                      "isPatchHidden": true
                    },
                    "layers": 1,
                    "matrix": [
                      1,
                      0,
                      0,
                      0,
                      0,
                      0.811064,
                      -0.584958,
                      0,
                      0,
                      0.584958,
                      0.811064,
                      0,
                      0,
                      0.38,
                      -0.5,
                      1
                    ],
                    "geometry": "E38C38A8-DA21-45A6-8C1F-FF913A555003",
                    "material": "4CBB5407-33B9-4512-9EAB-3617812A7823"
                  },
                  {
                    "uuid": "140AE697-D99E-4865-B533-5AC41AF2527C",
                    "type": "Mesh",
                    "name": "Back K",
                    "castShadow": true,
                    "receiveShadow": true,
                    "userData": {
                      "isPatchHidden": true
                    },
                    "layers": 1,
                    "matrix": [
                      1,
                      0,
                      0,
                      0,
                      0,
                      0,
                      -1,
                      0,
                      0,
                      1,
                      0,
                      0,
                      0,
                      0.75,
                      0.002907,
                      1
                    ],
                    "geometry": "9620A241-34A5-4BEC-8242-3E717FE32AE8",
                    "material": "B0076335-A2AD-42AD-8563-E7903168F5D4"
                  },
                  {
                    "uuid": "F161C80D-F7AE-4DA6-882A-42C45229E05A",
                    "type": "Mesh",
                    "name": "Bottom K",
                    "castShadow": true,
                    "receiveShadow": true,
                    "visible": false,
                    "userData": {
                      "isPatchHidden": true
                    },
                    "layers": 1,
                    "matrix": [
                      1,
                      0,
                      0,
                      0,
                      0,
                      1,
                      0,
                      0,
                      0,
                      0,
                      1,
                      0,
                      0,
                      0,
                      -0.5,
                      1
                    ],
                    "geometry": "249150A3-6DD8-4DA0-9103-DF6F86E5EC06",
                    "material": "460A2475-D38E-42DB-8787-7D8B829059CF"
                  },
                  {
                    "uuid": "A4AF186F-C28E-4E4E-AA40-470E5C380CE7",
                    "type": "Mesh",
                    "name": "Top K",
                    "castShadow": true,
                    "receiveShadow": true,
                    "visible": false,
                    "userData": {
                      "isPatchHidden": true
                    },
                    "layers": 1,
                    "matrix": [
                      1,
                      0,
                      0,
                      0,
                      0,
                      1,
                      0,
                      0,
                      0,
                      0,
                      1,
                      0,
                      0,
                      1.5,
                      -0.494401,
                      1
                    ],
                    "geometry": "68AB17BE-D311-4C8F-A4AA-EC7CBBAA44E1",
                    "material": "01C71024-FD33-49F5-921F-1B519E3F9831"
                  }
                ]
              }
            ]
          },
          {
            "uuid": "739E88EA-15C4-4714-86AB-EBDFFDB9BEBF",
            "type": "Group",
            "name": "L",
            "renderOrder": 2,
            "userData": {
              "isPatchHidden": true
            },
            "layers": 1,
            "matrix": [
              1,
              0,
              0,
              0,
              0,
              1,
              0,
              0,
              0,
              0,
              1,
              0,
              0,
              -1.5,
              2,
              1
            ],
            "children": [
              {
                "uuid": "B0D3C1BB-D093-45DD-9D0C-BF38BD58A4B4",
                "type": "Group",
                "name": "L Group",
                "userData": {
                  "isPatchHidden": true
                },
                "layers": 1,
                "matrix": [
                  1,
                  0,
                  0,
                  0,
                  0,
                  1,
                  0,
                  0,
                  0,
                  0,
                  1,
                  0,
                  0,
                  0,
                  0,
                  1
                ],
                "children": [
                  {
                    "uuid": "D14C7AAB-E1B9-4FC9-8CD6-057670B3ACF4",
                    "type": "Mesh",
                    "name": "Back L",
                    "castShadow": true,
                    "receiveShadow": true,
                    "userData": {
                      "isPatchHidden": true
                    },
                    "layers": 1,
                    "matrix": [
                      1,
                      0,
                      0,
                      0,
                      0,
                      0,
                      -1,
                      0,
                      0,
                      1,
                      0,
                      0,
                      0,
                      0.75,
                      0.002907,
                      1
                    ],
                    "geometry": "9620A241-34A5-4BEC-8242-3E717FE32AE8",
                    "material": "B0076335-A2AD-42AD-8563-E7903168F5D4"
                  },
                  {
                    "uuid": "223D325F-EC70-4957-AB9C-6AE87B5A7616",
                    "type": "Mesh",
                    "name": "Bottom L",
                    "castShadow": true,
                    "receiveShadow": true,
                    "userData": {
                      "isPatchHidden": true
                    },
                    "layers": 1,
                    "matrix": [
                      1,
                      0,
                      0,
                      0,
                      0,
                      1,
                      0,
                      0,
                      0,
                      0,
                      1,
                      0,
                      0,
                      0,
                      -0.5,
                      1
                    ],
                    "geometry": "249150A3-6DD8-4DA0-9103-DF6F86E5EC06",
                    "material": "460A2475-D38E-42DB-8787-7D8B829059CF"
                  }
                ]
              }
            ]
          },
          {
            "uuid": "1C7C58D7-4B76-4295-A305-3ECBECEF0AF0",
            "type": "Group",
            "name": "E",
            "renderOrder": 1,
            "userData": {
              "isPatchHidden": true
            },
            "layers": 1,
            "matrix": [
              1,
              0,
              0,
              0,
              0,
              1,
              0,
              0,
              0,
              0,
              1,
              0,
              0,
              -1.5,
              1,
              1
            ],
            "children": [
              {
                "uuid": "7BE1CB8C-45D1-4082-BC65-65B8FBE0054C",
                "type": "Group",
                "name": "E Group",
                "userData": {
                  "isPatchHidden": true
                },
                "layers": 1,
                "matrix": [
                  1,
                  0,
                  0,
                  0,
                  0,
                  1,
                  0,
                  0,
                  0,
                  0,
                  1,
                  0,
                  0,
                  0,
                  0,
                  1
                ],
                "children": [
                  {
                    "uuid": "53CD8FC2-11DD-4605-8C3E-B7AA2DB0004E",
                    "type": "Mesh",
                    "name": "Top E",
                    "castShadow": true,
                    "receiveShadow": true,
                    "userData": {
                      "isPatchHidden": true
                    },
                    "layers": 1,
                    "matrix": [
                      1,
                      0,
                      0,
                      0,
                      0,
                      1,
                      0,
                      0,
                      0,
                      0,
                      1,
                      0,
                      0,
                      1.5,
                      -0.494401,
                      1
                    ],
                    "geometry": "68AB17BE-D311-4C8F-A4AA-EC7CBBAA44E1",
                    "material": "01C71024-FD33-49F5-921F-1B519E3F9831"
                  },
                  {
                    "uuid": "AC0EEDB7-D100-4DAC-9CBE-4B35FD55E656",
                    "type": "Mesh",
                    "name": "Back E",
                    "castShadow": true,
                    "receiveShadow": true,
                    "frustumCulled": false,
                    "userData": {
                      "isPatchHidden": true
                    },
                    "layers": 1,
                    "matrix": [
                      1,
                      0,
                      0,
                      0,
                      0,
                      0,
                      -1,
                      0,
                      0,
                      1,
                      0,
                      0,
                      0,
                      0.75,
                      0.002907,
                      1
                    ],
                    "geometry": "9620A241-34A5-4BEC-8242-3E717FE32AE8",
                    "material": "B0076335-A2AD-42AD-8563-E7903168F5D4"
                  },
                  {
                    "uuid": "305D0EDB-DD9D-4363-BCB1-4162C7DF0A87",
                    "type": "Mesh",
                    "name": "Bottom E",
                    "castShadow": true,
                    "receiveShadow": true,
                    "userData": {
                      "isPatchHidden": true
                    },
                    "layers": 1,
                    "matrix": [
                      1,
                      0,
                      0,
                      0,
                      0,
                      1,
                      0,
                      0,
                      0,
                      0,
                      1,
                      0,
                      0,
                      0,
                      -0.5,
                      1
                    ],
                    "geometry": "249150A3-6DD8-4DA0-9103-DF6F86E5EC06",
                    "material": "460A2475-D38E-42DB-8787-7D8B829059CF"
                  },
                  {
                    "uuid": "69D4E565-6E1A-4C2F-BCDB-8E95B783C115",
                    "type": "Mesh",
                    "name": "Middle E",
                    "castShadow": true,
                    "receiveShadow": true,
                    "userData": {
                      "isPatchHidden": true
                    },
                    "layers": 1,
                    "matrix": [
                      1,
                      0,
                      0,
                      0,
                      0,
                      1,
                      0,
                      0,
                      0,
                      0,
                      1,
                      0,
                      0,
                      0.75,
                      -0.5,
                      1
                    ],
                    "geometry": "249150A3-6DD8-4DA0-9103-DF6F86E5EC06",
                    "material": "460A2475-D38E-42DB-8787-7D8B829059CF"
                  }
                ]
              }
            ]
          },
          {
            "uuid": "8C5C7E5D-6C0B-489F-AF98-FEE5ECFDB98E",
            "type": "Group",
            "name": "S",
            "renderOrder": 1,
            "userData": {
              "isPatchHidden": true
            },
            "layers": 1,
            "matrix": [
              1,
              0,
              0,
              0,
              0,
              1,
              0,
              0,
              0,
              0,
              1,
              0,
              0,
              -1.5,
              0,
              1
            ],
            "children": [
              {
                "uuid": "E6F7FF1F-2248-4788-AF89-4D9658952800",
                "type": "Group",
                "name": "S Group",
                "userData": {
                  "isPatchHidden": true
                },
                "layers": 1,
                "matrix": [
                  1,
                  0,
                  0,
                  0,
                  0,
                  1,
                  0,
                  0,
                  0,
                  0,
                  1,
                  0,
                  0,
                  0,
                  0,
                  1
                ],
                "children": [
                  {
                    "uuid": "FC7FB5F5-E3F5-43B3-875A-84BD0A01749C",
                    "type": "Mesh",
                    "name": "Top S",
                    "castShadow": true,
                    "receiveShadow": true,
                    "userData": {
                      "isPatchHidden": true
                    },
                    "layers": 1,
                    "matrix": [
                      1,
                      0,
                      0,
                      0,
                      0,
                      1,
                      0,
                      0,
                      0,
                      0,
                      1,
                      0,
                      0,
                      1.5,
                      -0.494401,
                      1
                    ],
                    "geometry": "68AB17BE-D311-4C8F-A4AA-EC7CBBAA44E1",
                    "material": "01C71024-FD33-49F5-921F-1B519E3F9831"
                  },
                  {
                    "uuid": "7A2B9C40-5A72-4434-8F42-D3B5DC10F694",
                    "type": "Mesh",
                    "name": "Back S",
                    "castShadow": true,
                    "receiveShadow": true,
                    "frustumCulled": false,
                    "userData": {
                      "isPatchHidden": true
                    },
                    "layers": 1,
                    "matrix": [
                      1,
                      0,
                      0,
                      0,
                      0,
                      0,
                      -1,
                      0,
                      0,
                      1,
                      0,
                      0,
                      0,
                      1.13,
                      0.002907,
                      1
                    ],
                    "geometry": "F2481688-8870-42FC-917C-9CEADAF9D0B3",
                    "material": "B0076335-A2AD-42AD-8563-E7903168F5D4"
                  },
                  {
                    "uuid": "366D1E66-5474-4AF0-B0EE-5A0056A0B63B",
                    "type": "Mesh",
                    "name": "Bottom E",
                    "castShadow": true,
                    "receiveShadow": true,
                    "userData": {
                      "isPatchHidden": true
                    },
                    "layers": 1,
                    "matrix": [
                      1,
                      0,
                      0,
                      0,
                      0,
                      1,
                      0,
                      0,
                      0,
                      0,
                      1,
                      0,
                      0,
                      0,
                      -0.5,
                      1
                    ],
                    "geometry": "249150A3-6DD8-4DA0-9103-DF6F86E5EC06",
                    "material": "460A2475-D38E-42DB-8787-7D8B829059CF"
                  },
                  {
                    "uuid": "59687F32-98F5-4BFE-BE1A-453C92225CF9",
                    "type": "Mesh",
                    "name": "Middle E",
                    "castShadow": true,
                    "receiveShadow": true,
                    "userData": {
                      "isPatchHidden": true
                    },
                    "layers": 1,
                    "matrix": [
                      1,
                      0,
                      0,
                      0,
                      0,
                      1,
                      0,
                      0,
                      0,
                      0,
                      1,
                      0,
                      0,
                      0.75,
                      -0.5,
                      1
                    ],
                    "geometry": "249150A3-6DD8-4DA0-9103-DF6F86E5EC06",
                    "material": "460A2475-D38E-42DB-8787-7D8B829059CF"
                  }
                ]
              }
            ]
          },
          {
            "uuid": "8A455DB7-7F44-4EF6-B201-84741317443D",
            "type": "Group",
            "name": "S",
            "renderOrder": 1,
            "userData": {
              "isPatchHidden": true
            },
            "layers": 1,
            "matrix": [
              1,
              0,
              0,
              0,
              0,
              1,
              0,
              0,
              0,
              0,
              1,
              0,
              0,
              -1.5,
              -1,
              1
            ],
            "children": [
              {
                "uuid": "4DCD62E3-DD01-4899-BDFA-38664B2DA09A",
                "type": "Group",
                "name": "S Group",
                "userData": {
                  "isPatchHidden": true
                },
                "layers": 1,
                "matrix": [
                  1,
                  0,
                  0,
                  0,
                  0,
                  1,
                  0,
                  0,
                  0,
                  0,
                  1,
                  0,
                  0,
                  0,
                  0,
                  1
                ],
                "children": [
                  {
                    "uuid": "03A7B1F6-EBB8-4362-8916-DDC392A6F8DB",
                    "type": "Mesh",
                    "name": "Top S",
                    "castShadow": true,
                    "receiveShadow": true,
                    "userData": {
                      "isPatchHidden": true
                    },
                    "layers": 1,
                    "matrix": [
                      1,
                      0,
                      0,
                      0,
                      0,
                      1,
                      0,
                      0,
                      0,
                      0,
                      1,
                      0,
                      0,
                      1.5,
                      -0.494401,
                      1
                    ],
                    "geometry": "68AB17BE-D311-4C8F-A4AA-EC7CBBAA44E1",
                    "material": "01C71024-FD33-49F5-921F-1B519E3F9831"
                  },
                  {
                    "uuid": "4F6DBBEA-0D29-4E20-B577-AB8E28704E6D",
                    "type": "Mesh",
                    "name": "Back S",
                    "castShadow": true,
                    "receiveShadow": true,
                    "frustumCulled": false,
                    "userData": {
                      "isPatchHidden": true
                    },
                    "layers": 1,
                    "matrix": [
                      1,
                      0,
                      0,
                      0,
                      0,
                      0,
                      -1,
                      0,
                      0,
                      1,
                      0,
                      0,
                      0,
                      1.13,
                      0.002907,
                      1
                    ],
                    "geometry": "F2481688-8870-42FC-917C-9CEADAF9D0B3",
                    "material": "B0076335-A2AD-42AD-8563-E7903168F5D4"
                  },
                  {
                    "uuid": "5A9D88A1-DCAE-4933-87A2-788BCBA164E1",
                    "type": "Mesh",
                    "name": "Bottom E",
                    "castShadow": true,
                    "receiveShadow": true,
                    "userData": {
                      "isPatchHidden": true
                    },
                    "layers": 1,
                    "matrix": [
                      1,
                      0,
                      0,
                      0,
                      0,
                      1,
                      0,
                      0,
                      0,
                      0,
                      1,
                      0,
                      0,
                      0,
                      -0.5,
                      1
                    ],
                    "geometry": "249150A3-6DD8-4DA0-9103-DF6F86E5EC06",
                    "material": "460A2475-D38E-42DB-8787-7D8B829059CF"
                  },
                  {
                    "uuid": "7B37715C-049C-41A5-B341-7CE09ABCFA1D",
                    "type": "Mesh",
                    "name": "Middle E",
                    "castShadow": true,
                    "receiveShadow": true,
                    "userData": {
                      "isPatchHidden": true
                    },
                    "layers": 1,
                    "matrix": [
                      1,
                      0,
                      0,
                      0,
                      0,
                      1,
                      0,
                      0,
                      0,
                      0,
                      1,
                      0,
                      0,
                      0.75,
                      -0.5,
                      1
                    ],
                    "geometry": "249150A3-6DD8-4DA0-9103-DF6F86E5EC06",
                    "material": "460A2475-D38E-42DB-8787-7D8B829059CF"
                  }
                ]
              }
            ]
          },
          {
            "uuid": "D13AAF7C-D8D0-441B-A04E-B11722F81CD0",
            "type": "Group",
            "name": "T",
            "userData": {
              "isPatchHidden": true
            },
            "layers": 1,
            "matrix": [
              1,
              0,
              0,
              0,
              0,
              1,
              0,
              0,
              0,
              0,
              1,
              0,
              0,
              -3,
              2,
              1
            ],
            "children": [
              {
                "uuid": "6C0CB751-35B5-4870-B935-5F34CB65B365",
                "type": "Group",
                "name": "T Group",
                "userData": {
                  "isPatchHidden": true
                },
                "layers": 1,
                "matrix": [
                  1,
                  0,
                  0,
                  0,
                  0,
                  1,
                  0,
                  0,
                  0,
                  0,
                  1,
                  0,
                  0,
                  0,
                  0,
                  1
                ],
                "children": [
                  {
                    "uuid": "B697350A-B94C-46AA-9F33-B63FE31FEA72",
                    "type": "Mesh",
                    "name": "Top T",
                    "castShadow": true,
                    "receiveShadow": true,
                    "userData": {
                      "isPatchHidden": true
                    },
                    "layers": 1,
                    "matrix": [
                      1,
                      0,
                      0,
                      0,
                      0,
                      1,
                      0,
                      0,
                      0,
                      0,
                      1,
                      0,
                      0,
                      1.5,
                      -0.494401,
                      1
                    ],
                    "geometry": "68AB17BE-D311-4C8F-A4AA-EC7CBBAA44E1",
                    "material": "01C71024-FD33-49F5-921F-1B519E3F9831"
                  },
                  {
                    "uuid": "E0348037-3227-4E21-953F-922B0793926F",
                    "type": "Mesh",
                    "name": "Bar T",
                    "castShadow": true,
                    "receiveShadow": true,
                    "userData": {
                      "isPatchHidden": true
                    },
                    "layers": 1,
                    "matrix": [
                      1,
                      0,
                      0,
                      0,
                      0,
                      0,
                      -1,
                      0,
                      0,
                      1,
                      0,
                      0,
                      0,
                      0.75,
                      -0.5,
                      1
                    ],
                    "geometry": "9620A241-34A5-4BEC-8242-3E717FE32AE8",
                    "material": "B0076335-A2AD-42AD-8563-E7903168F5D4"
                  }
                ]
              }
            ]
          },
          {
            "uuid": "D15342C4-ACEE-424E-9029-BADAD98E0A16",
            "type": "Group",
            "name": "E",
            "renderOrder": 1,
            "userData": {
              "isPatchHidden": true
            },
            "layers": 1,
            "matrix": [
              1,
              0,
              0,
              0,
              0,
              1,
              0,
              0,
              0,
              0,
              1,
              0,
              0,
              -3,
              1,
              1
            ],
            "children": [
              {
                "uuid": "7E3D0AD1-D5E7-4FCD-9A4C-9880FBDAEC7A",
                "type": "Group",
                "name": "E Group",
                "userData": {
                  "isPatchHidden": true
                },
                "layers": 1,
                "matrix": [
                  1,
                  0,
                  0,
                  0,
                  0,
                  1,
                  0,
                  0,
                  0,
                  0,
                  1,
                  0,
                  0,
                  0,
                  0,
                  1
                ],
                "children": [
                  {
                    "uuid": "40CEE30B-CAD6-4E21-84B7-0135CEE193F3",
                    "type": "Mesh",
                    "name": "Top E",
                    "castShadow": true,
                    "receiveShadow": true,
                    "userData": {
                      "isPatchHidden": true
                    },
                    "layers": 1,
                    "matrix": [
                      1,
                      0,
                      0,
                      0,
                      0,
                      1,
                      0,
                      0,
                      0,
                      0,
                      1,
                      0,
                      0,
                      1.5,
                      -0.494401,
                      1
                    ],
                    "geometry": "68AB17BE-D311-4C8F-A4AA-EC7CBBAA44E1",
                    "material": "01C71024-FD33-49F5-921F-1B519E3F9831"
                  },
                  {
                    "uuid": "BA332B2E-B012-4B0B-B089-2E1215CB5BAF",
                    "type": "Mesh",
                    "name": "Back E",
                    "castShadow": true,
                    "receiveShadow": true,
                    "frustumCulled": false,
                    "userData": {
                      "isPatchHidden": true
                    },
                    "layers": 1,
                    "matrix": [
                      1,
                      0,
                      0,
                      0,
                      0,
                      0,
                      -1,
                      0,
                      0,
                      1,
                      0,
                      0,
                      0,
                      0.75,
                      0.002907,
                      1
                    ],
                    "geometry": "9620A241-34A5-4BEC-8242-3E717FE32AE8",
                    "material": "B0076335-A2AD-42AD-8563-E7903168F5D4"
                  },
                  {
                    "uuid": "930C2668-AEA6-4646-928B-C0B448881D16",
                    "type": "Mesh",
                    "name": "Bottom E",
                    "castShadow": true,
                    "receiveShadow": true,
                    "userData": {
                      "isPatchHidden": true
                    },
                    "layers": 1,
                    "matrix": [
                      1,
                      0,
                      0,
                      0,
                      0,
                      1,
                      0,
                      0,
                      0,
                      0,
                      1,
                      0,
                      0,
                      0,
                      -0.5,
                      1
                    ],
                    "geometry": "249150A3-6DD8-4DA0-9103-DF6F86E5EC06",
                    "material": "460A2475-D38E-42DB-8787-7D8B829059CF"
                  },
                  {
                    "uuid": "517CBAD4-38C1-4CE6-A8F6-79EAFE0C4B5B",
                    "type": "Mesh",
                    "name": "Middle E",
                    "castShadow": true,
                    "receiveShadow": true,
                    "userData": {
                      "isPatchHidden": true
                    },
                    "layers": 1,
                    "matrix": [
                      1,
                      0,
                      0,
                      0,
                      0,
                      1,
                      0,
                      0,
                      0,
                      0,
                      1,
                      0,
                      0,
                      0.75,
                      -0.5,
                      1
                    ],
                    "geometry": "249150A3-6DD8-4DA0-9103-DF6F86E5EC06",
                    "material": "460A2475-D38E-42DB-8787-7D8B829059CF"
                  }
                ]
              }
            ]
          },
          {
            "uuid": "A5F50881-79E1-4BAB-B430-38F7A58E6F89",
            "type": "Group",
            "name": "C",
            "renderOrder": 2,
            "userData": {
              "isPatchHidden": true
            },
            "layers": 1,
            "matrix": [
              1,
              0,
              0,
              0,
              0,
              1,
              0,
              0,
              0,
              0,
              1,
              0,
              0,
              -3,
              0,
              1
            ],
            "children": [
              {
                "uuid": "116A744C-7BE2-4357-9CA2-C63F06022C14",
                "type": "Group",
                "name": "C Group",
                "userData": {
                  "isPatchHidden": true
                },
                "layers": 1,
                "matrix": [
                  1,
                  0,
                  0,
                  0,
                  0,
                  1,
                  0,
                  0,
                  0,
                  0,
                  1,
                  0,
                  0,
                  0,
                  0,
                  1
                ],
                "children": [
                  {
                    "uuid": "EA9A9150-597A-43A3-B67E-FAE7210359E8",
                    "type": "Mesh",
                    "name": "Top C",
                    "castShadow": true,
                    "receiveShadow": true,
                    "userData": {
                      "isPatchHidden": true
                    },
                    "layers": 1,
                    "matrix": [
                      1,
                      0,
                      0,
                      0,
                      0,
                      1,
                      0,
                      0,
                      0,
                      0,
                      1,
                      0,
                      0,
                      1.5,
                      -0.5,
                      1
                    ],
                    "geometry": "68AB17BE-D311-4C8F-A4AA-EC7CBBAA44E1",
                    "material": "01C71024-FD33-49F5-921F-1B519E3F9831"
                  },
                  {
                    "uuid": "A6CB530D-2002-442C-BF22-FC577D1B551B",
                    "type": "Mesh",
                    "name": "Back C",
                    "castShadow": true,
                    "receiveShadow": true,
                    "userData": {
                      "isPatchHidden": true
                    },
                    "layers": 1,
                    "matrix": [
                      1,
                      0,
                      0,
                      0,
                      0,
                      0,
                      -1,
                      0,
                      0,
                      1,
                      0,
                      0,
                      0,
                      0.75,
                      0.002907,
                      1
                    ],
                    "geometry": "9620A241-34A5-4BEC-8242-3E717FE32AE8",
                    "material": "B0076335-A2AD-42AD-8563-E7903168F5D4"
                  },
                  {
                    "uuid": "F9C8C751-136B-495F-9023-08917FEE6BA8",
                    "type": "Mesh",
                    "name": "Bottom C",
                    "castShadow": true,
                    "receiveShadow": true,
                    "userData": {
                      "isPatchHidden": true
                    },
                    "layers": 1,
                    "matrix": [
                      1,
                      0,
                      0,
                      0,
                      0,
                      1,
                      0,
                      0,
                      0,
                      0,
                      1,
                      0,
                      0,
                      0,
                      -0.5,
                      1
                    ],
                    "geometry": "249150A3-6DD8-4DA0-9103-DF6F86E5EC06",
                    "material": "460A2475-D38E-42DB-8787-7D8B829059CF"
                  }
                ]
              }
            ]
          },
          {
            "uuid": "8062A59F-CFBF-45E4-A0F4-EF84CDED1A89",
            "type": "Group",
            "name": "H",
            "renderOrder": 1,
            "userData": {
              "isPatchHidden": true
            },
            "layers": 1,
            "matrix": [
              1,
              0,
              0,
              0,
              0,
              1,
              0,
              0,
              0,
              0,
              1,
              0,
              0,
              -3,
              -1,
              1
            ],
            "children": [
              {
                "uuid": "C89CAF61-8688-4630-84FC-BF69530AA5FD",
                "type": "Group",
                "name": "H Group",
                "userData": {
                  "isPatchHidden": true
                },
                "layers": 1,
                "matrix": [
                  1,
                  0,
                  0,
                  0,
                  0,
                  1,
                  0,
                  0,
                  0,
                  0,
                  1,
                  0,
                  0,
                  0,
                  0,
                  1
                ],
                "children": [
                  {
                    "uuid": "CBF97B92-3C65-4860-84B9-C6F344348B31",
                    "type": "Mesh",
                    "name": "Front H",
                    "castShadow": true,
                    "receiveShadow": true,
                    "frustumCulled": false,
                    "userData": {
                      "isPatchHidden": true
                    },
                    "layers": 1,
                    "matrix": [
                      1,
                      0,
                      0,
                      0,
                      0,
                      0,
                      -1,
                      0,
                      0,
                      1,
                      0,
                      0,
                      0,
                      0.75,
                      -1,
                      1
                    ],
                    "geometry": "9620A241-34A5-4BEC-8242-3E717FE32AE8",
                    "material": "B0076335-A2AD-42AD-8563-E7903168F5D4"
                  },
                  {
                    "uuid": "6C78D985-FD59-491A-A1FD-0BC708AE48AC",
                    "type": "Mesh",
                    "name": "Back H",
                    "castShadow": true,
                    "receiveShadow": true,
                    "frustumCulled": false,
                    "userData": {
                      "isPatchHidden": true
                    },
                    "layers": 1,
                    "matrix": [
                      1,
                      0,
                      0,
                      0,
                      0,
                      0,
                      -1,
                      0,
                      0,
                      1,
                      0,
                      0,
                      0,
                      0.75,
                      0.002907,
                      1
                    ],
                    "geometry": "9620A241-34A5-4BEC-8242-3E717FE32AE8",
                    "material": "B0076335-A2AD-42AD-8563-E7903168F5D4"
                  },
                  {
                    "uuid": "398FED68-5564-46CF-AEC9-654744A82EDE",
                    "type": "Mesh",
                    "name": "Middle H",
                    "castShadow": true,
                    "receiveShadow": true,
                    "userData": {
                      "isPatchHidden": true
                    },
                    "layers": 1,
                    "matrix": [
                      1,
                      0,
                      0,
                      0,
                      0,
                      1,
                      0,
                      0,
                      0,
                      0,
                      1,
                      0,
                      0,
                      0.75,
                      -0.5,
                      1
                    ],
                    "geometry": "249150A3-6DD8-4DA0-9103-DF6F86E5EC06",
                    "material": "460A2475-D38E-42DB-8787-7D8B829059CF"
                  }
                ]
              }
            ]
          }
        ]
      },
      {
        "uuid": "DBBD9C2E-4D8E-4628-9427-9DEBA682526C",
        "type": "Mesh",
        "name": "Floor",

        "receiveShadow": true,
        "userData": {
          "isPatchHidden": true
        },
        "layers": 1,
        "matrix": [
          1,
          0,
          0,
          0,
          0,
          0,
          -1,
          0,
          0,
          1,
          0,
          0,
          0,
          0,
          0,
          1
        ],
        "geometry": "141ECD77-67FA-4117-A044-8623F4059DCF",
        "material": "1CBA7500-7DA7-4062-9F37-9071B8807F4F"
      },
      {
        "uuid": "D918E61C-AFE0-4C93-B3D2-99FD9F020FC2",
        "type": "SpotLight",
        "name": "SpotLight",
        "castShadow": true,
        "userData": {
          "isPatchHidden": true
        },
        "layers": 1,
        "matrix": [
          1,
          0,
          0,
          0,
          0,
          1,
          0,
          0,
          0,
          0,
          1,
          0,
          -5,
          10,
          7.5,
          1
        ],
        "color": 16777215,
        "intensity": 1,
        "distance": 0,
        "angle": 0.314159,
        "decay": 1,
        "penumbra": 0,
        "shadow": {
          "camera": {
            "uuid": "F99E4F32-37E2-42E6-8E9A-A6F0D0DF89AD",
            "type": "PerspectiveCamera",
            "layers": 1,
            "fov": 36,
            "zoom": 1,
            "near": 0.5,
            "far": 500,
            "focus": 10,
            "aspect": 1,
            "filmGauge": 35,
            "filmOffset": 0
          }
        }
      }
    ]
  },
  "connections": [
    {
      "uuid": "dfaef11e-3e59-4220-9286-df5c3255429a",
      "from": "7ea68760-0c58-4378-8bad-076477a3726e",
      "fromProp": "position",
      "to": "3948a8d7-dd32-4ca8-9c0f-f28a1dff3e10",
      "toProp": "value"
    },
    {
      "uuid": "d675dd59-f332-4510-858c-bf8f4523c844",
      "from": "3948a8d7-dd32-4ca8-9c0f-f28a1dff3e10",
      "fromProp": "value",
      "to": "1F0AFF04-BE32-494A-A764-1137A90E3D4B",
      "toProp": "position"
    }
  ],
  "generators": [
    {
      "uuid": "7ea68760-0c58-4378-8bad-076477a3726e",
      "type": "Sinewave",
      "name": "Sinewave",
      "resolution": 32,
      "rpm": 30,
      "looped": true,
      "paused": false
    }
  ],
  "devices": [],
  "peers": [],
  "transforms": [
    {
      "uuid": "3948a8d7-dd32-4ca8-9c0f-f28a1dff3e10",
      "type": "Multiply",
      "name": "Multiply",
      "amount": 2
    }
  ]
}